[{"head": "university", "head_type": "ORGANIZATION", "relation": "has", "tail": "students with Disabilities and SLD", "tail_type": "GROUP"}, {"head": "students with Disabilities and SLD", "head_type": "GROUP", "relation": "has", "tail": "paid hours per year, with flexible hours", "tail_type": "OBJECT"}, {"head": "paid hours per year, with flexible hours", "head_type": "OBJECT", "relation": "has", "tail": "to support", "tail_type": "ACTION"}, {"head": "to support", "head_type": "ACTION", "relation": "has", "tail": "students with Disabilities and SLD", "tail_type": "GROUP"}, {"head": "students with Disabilities and SLD", "head_type": "GROUP", "relation": "has", "tail": "at the university", "tail_type": "LOCATION"}, {"head": "at the university", "head_type": "LOCATION", "relation": "has", "tail": "university", "tail_type": "ORGANIZATION"}, {"head": "university", "head_type": "ORGANIZATION", "relation": "has", "tail": "Published on", "tail_type": "EVENT"}, {"head": "Published on", "head_type": "EVENT", "relation": "has", "tail": "27 June 2024", "tail_type": "DATE"}, {"head": "27 June 2024", "head_type": "DATE", "relation": "has", "tail": "Link:", "tail_type": "OBJECT"}, {"head": "Link:", "head_type": "OBJECT", "relation": "has", "tail": "https://bandi.unibo.it/agevolazioni/assegni-tutorato?str=amministrazione-generale", "tail_type": "URL"}, {"head": "https://bandi.unibo.it/agevolazioni/assegni-tutorato?str=amministrazione-generale", "head_type": "URL", "relation": "has", "tail": "Apply for the call.", "tail_type": "ACTION"}, {"head": "Apply for the call.", "head_type": "ACTION", "relation": "has", "tail": "Deadline:", "tail_type": "EVENT"}, {"head": "Deadline:", "head_type": "EVENT", "relation": "has", "tail": "1 August.", "tail_type": "DATE"}, [{"head": "university", "head_type": "ORGANIZATION", "relation": "has", "tail": "students with Disabilities and SLD", "tail_type": "GROUP"}, {"head": "students with Disabilities and SLD", "head_type": "GROUP", "relation": "has", "tail": "paid hours per year, with flexible hours", "tail_type": "OBJECT"}, {"head": "paid hours per year, with flexible hours", "head_type": "OBJECT", "relation": "has", "tail": "to support", "tail_type": "ACTION"}, {"head": "to support", "head_type": "ACTION", "relation": "has", "tail": "students with Disabilities and SLD", "tail_type": "GROUP"}, {"head": "students with Disabilities and SLD", "head_type": "GROUP", "relation": "has", "tail": "at the university", "tail_type": "LOCATION"}, {"head": "at the university", "head_type": "LOCATION", "relation": "has", "tail": "university", "tail_type": "ORGANIZATION"}, {"head": "university", "head_type": "ORGANIZATION", "relation": "has", "tail": "Published on", "tail_type": "EVENT"}, {"head": "Published on", "head_type": "EVENT", "relation": "has", "tail": "27 June 2024", "tail_type": "DATE"}, {"head": "27"}]]