[{"head": "University", "head_type": "ORGANIZATION", "relation": "located_in", "tail": "Bologna", "tail_type": "CITY"}, [{"head": "Universit\u00e0 di Bologna", "head_type": "ORGANIZATION", "relation": "located_in", "tail": "Bologna", "tail_type": "CITY"}], {"head": "App", "head_type": "SOFTWARE", "relation": "uses", "tail": "University", "tail_type": "ORGANIZATION"}, [{"head": "App", "head_type": "SOFTWARE", "relation": "uses", "tail": "Universit\u00e0 di Bologna", "tail_type": "ORGANIZATION"}], {"head": "University", "head_type": "ORGANIZATION", "relation": "has", "tail": "trademark", "tail_type": "PROPERTY"}, [{"head": "Universit\u00e0 di Bologna", "head_type": "ORGANIZATION", "relation": "has", "tail": "University trademark", "tail_type": "PROPERTY"}], {"head": "University", "head_type": "ORGANIZATION", "relation": "located_at", "tail": "Via Zamboni, 33", "tail_type": "STREET"}, [{"head": "Universit\u00e0 di Bologna", "head_type": "ORGANIZATION", "relation": "located_at", "tail": "Via Zamboni, 33", "tail_type": "STREET"}], {"head": "University", "head_type": "ORGANIZATION", "relation": "has", "tail": "ALMA MATER STUDIORUM", "tail_type": "NAME"}, [{"head": "Universit\u00e0 di Bologna", "head_type": "ORGANIZATION", "relation": "has", "tail": "ALMA MATER STUDIORUM", "tail_type": "NAME"}], {"head": "University", "head_type": "ORGANIZATION", "relation": "located_in", "tail": "Italy", "tail_type": "COUNTRY"}, [{"head": "Universit\u00e0 di Bologna", "head_type": "ORGANIZATION", "relation": "located_in", "tail": "Italy", "tail_type": "COUNTRY"}], {"head": "University", "head_type": "ORGANIZATION", "relation": "has", "tail": "Privacy Legal notes", "tail_type": "DOCUMENT"}, [{"head": "Universit\u00e0 di Bologna", "head_type": "ORGANIZATION", "relation": "has", "tail": "Privacy Legal notes", "tail_type": "DOCUMENT"}], {"head": "University", "head_type": "ORGANIZATION", "relation": "located_in", "tail": "40126", "tail_type": "ZIPCODE"}, [{"head": "Universit\u00e0 di Bologna", "head_type": "ORGANIZATION", "relation": "located_in", "tail": "40126", "tail_type": "ZIPCODE"}], {"head": "University", "head_type": "ORGANIZATION", "relation": "has", "tail": "Cookie settings", "tail_type": "SETTING"}, [{"head": "Universit\u00e0 di Bologna", "head_type": "ORGANIZATION", "relation": "has", "tail": "Cookie settings", "tail_type": "SETTING"}], {"head": "University", "head_type": "ORGANIZATION", "relation": "located_in", "tail": "Bologna", "tail_type": "CITY"}, [{"head": "Universit\u00e0 di Bologna", "head_type": "ORGANIZATION", "relation": "located_in", "tail": "Bologna", "tail_type": "CITY"}], {"head": "University", "head_type": ""}]