[[{"head": "Ingegneria e scienze informatiche", "head_type": "Domain", "relation": "has_objective", "tail": "formare la figura professionale dello Specialista in Ingegneria e Scienze Informatiche", "tail_type": "Description"}, {"head": "Cesena", "head_type": "Location", "relation": "hosts", "tail": "Corso di Laurea Magistrale", "tail_type": "Program"}, {"head": "Laurea Magistrale", "head_type": "Education", "relation": "offers", "tail": "Ingegneria e scienze informatiche", "tail_type": "Major"}, {"head": "Specialista in Ingegneria e Scienze Informatiche", "head_type": "Profession", "relation": "has_objective", "tail": "formare la figura professionale", "tail_type": "Description"}, {"head": "Competenze specialistiche informatiche trasversali", "head_type": "Skill", "relation": "covered_by", "tail": "Corso di Laurea Magistrale", "tail_type": "Program"}, {"head": "Analisi, progettazione e gestione di sistemi informativi, web e di rete", "head_type": "Skill", "relation": "covered_by", "tail": "Corso di Laurea Magistrale", "tail_type": "Program"}, {"head": "Progettazione di sistemi embedded e infrastrutture", "head_type": "Skill", "relation": "covered_by", "tail": "Corso di Laurea Magistrale", "tail_type": "Program"}], [{"head": "Ingegneria e scienze informatiche", "head_type": "Domain", "relation": "has_objective", "tail": "formare la figura professionale dello Specialista in Ingegneria e Scienze Informatiche", "tail_type": "Description"}, {"head": "Cesena", "head_type": "Location", "relation": "hosts", "tail": "Corso di Laurea Magistrale", "tail_type": "Program"}, {"head": "Laurea Magistrale", "head_type": "Education", "relation": "offers", "tail": "Ingegneria e scienze informatiche", "tail_type": "Major"}, {"head": "Specialista in Ingegneria e Scienze Informatiche", "head_type": "Profession", "relation": "has_objective", "tail": "formare la figura professionale", "tail_type": "Description"}, {"head": "Competenze specialistiche informatiche trasversali", "head_type": "Skill", "relation": "covered_by", "tail": "Corso di Laurea Magistrale", "tail_type": "Program"}, {"head": "Analisi, progettazione e gestione di sistemi informativi, web e di rete", "head_type": "Skill", "relation": "covered_by", "tail": "Corso di Laurea Magistrale", "tail_type": "Program"}, {"head": "Progettazione di sistemi embedded e infrastrutture", "head_type": "Skill", "relation": "covered_by", "tail": "Corso di Laurea Magistrale", "tail_type": "Program"}], [{"head": "Ingegneria e scienze informatiche", "head_type": "Domain", "relation": "has_objective", "tail": "formare la figura professionale dello Specialista in Ingegneria e Scienze Informatiche", "tail_type": "Description"}, {"head": "Cesena", "head_type": "Location", "relation": "hosts", "tail": "Corso di Laurea Magistrale", "tail_type": "Program"}, {"head": "Laurea Magistrale"}]]