[[{"head": "University of Bologna", "head_type": "Organization", "relation": "is", "tail": "ALMA MATER STUDIORUM", "tail_type": "Organization"}, {"head": "Facebook", "head_type": "SocialMedia", "relation": "has", "tail": "http://www.facebook.com/unibo.it", "tail_type": "URL"}, {"head": "Twitter", "head_type": "SocialMedia", "relation": "has", "tail": "http://www.twitter.com/Unibo", "tail_type": "URL"}, {"head": "LinkedIn", "head_type": "SocialMedia", "relation": "has", "tail": "https://www.linkedin.com/edu/school?id=13901", "tail_type": "URL"}, {"head": "YouTube", "head_type": "SocialMedia", "relation": "has", "tail": "https://www.youtube.com/user/UniBologna", "tail_type": "URL"}, {"head": "Telegram", "head_type": "SocialMedia", "relation": "has", "tail": "https://t.me/Unibo_Official", "tail_type": "URL"}, {"head": "Instagram", "head_type": "SocialMedia", "relation": "has", "tail": "https://www.instagram.com/unibo/", "tail_type": "URL"}, {"head": "TikTok", "head_type": "SocialMedia", "relation": "has", "tail": "https://www.tiktok.com/@joinunibo", "tail_type": "URL"}, {"head": "Spreaker", "head_type": "SocialMedia", "relation": "has", "tail": "https://www.spreaker.com/user/unibo", "tail_type": "URL"}, {"head": "myUniBo", "head_type": "App", "relation": "has", "tail": "https://www.unibo.it/en/university/university-of-bologna-app/myunibo-app", "tail_type": "URL"}, {"head": "myAlmaOrienta", "head_type": "App", "relation": "has", "tail": "https://www.unibo.it/en/university/university-of-bologna-app/app-myalmaorienta", "tail_type": "URL"}, {"head": "App Job Placement", "head_type": "App", "relation": "has", "tail": "https://www.unibo.it/en/university/university-of-bologna-app/job-placement-unibo-app", "tail_type": "URL"}, {"head": "App Alumni", "head_type": "App", "relation": "has", "tail": "https://site.unibo.it/alumni-association/it", "tail_type": "URL"}, {"head": "ALMA MATER STUDIORUM", "head_type": "Organization", "relation": "is", "tail": "Universit\u00e0 di Bologna", "tail_type": "Organization"}], [{"head": "University of Bologna", "head_type": "Organization", "relation": "is", "tail": "ALMA MATER STUDIORUM", "tail_type": "Organization"}, {"head": "Facebook", "head_type": "SocialMedia", "relation": "has", "tail": "http://www.facebook.com/unibo.it", "tail_type": "URL"}, {"head": "Twitter", "head_type": "SocialMedia"}]]