[["Franco Callegati](https://www.unibo.it/sitoweb/franco.callegati)\n*   Prof. [Antonella Carbonaro](https://www.unibo.it/sitoweb/antonella.carbonaro)\n*   Prof. [Silvia Mirri](https://www.unibo.it/sitoweb/silvia.mirri)\n\nCommissione Gestione AQ e altre \u2014 Ingegneria e scienze informatiche - Laurea Magistrale - Cesena\n\n**Output:**\n\n[\n    {", "head", "Commissione di gestione AQ", "head_type", "Commissione", "relation", "supporta", "tail", "il Coordinatore", "tail_type", "Persona"], {"head": "Commissione Didattica", "head_type": "Commissione", "relation": "coadiuva", "tail": "il Coordinatore di Corso di studio", "tail_type": "Persona"}, {"head": "Commissione Pratiche Studenti", "head_type": "Commissione", "relation": "valuta", "tail": "l'ammissibilit\u00e0 degli studenti", "tail_type": "Evento"}, {"head": "Commissione Tirocinio in preparazione della prova finale", "head_type": "Commissione", "relation": "approva", "tail": "le domande di tirocinio", "tail_type": "Evento"}, {"head": "Commissione Orario delle lezioni", "head_type": "Commissione", "relation": "pianifica", "tail": "l'orario delle lezioni", "tail_type": "Evento"}, {"head": "Mario Bravetti", "head_type": "Persona", "relation": "Referente", "tail": "Commissione Didattica", "tail_type": "Commissione"}, {"head": "Franco Callegati", "head_type": "Persona", "relation": "Componente", "tail": "Commissione Orario delle lezioni", "tail_type": "Commissione"}, {"head": "Antonella Carbonaro", "head_type": "Persona", "relation": "Componente", "tail": "Commissione Orario delle lezioni", "tail_type": "Commissione"}, {"head": "Silvia Mirri", "head_type": "Persona", "relation": "Componente", "tail": "Commissione Orario delle lezioni", "tail_type": "Commissione"}, {"head": "Andrea Roli", "head_type": "Persona", "relation": "Componente", "tail": "Commissione Pratiche Studenti", "tail_type": "Commissione"}, {"head": "Alessandro Ricci", "head_type": "Persona", "relation": "Componente", "tail": "Commissione Pratiche Studenti", "tail_type": "Commissione"}, {"head": "Roberto Girau", "head_type": "Persona", "relation": "Componente", "tail": "Commissione Pratiche Studenti", "tail_type": "Commissione"}, {"head": "Damiana Lazzaro", "head_type": "Persona", "relation": "Componente", "tail": "Commissione Tirocinio in preparazione della prova finale", "tail_type": "Commissione"}, {"head": "Mirko Viroli", "head_type": "Persona", "relation": "Componente", "tail": "Commissione Tirocinio in preparazione della prova finale", "tail_type": "Commissione"}, [{"head": "Commissione di gestione AQ", "head_type": "Commissione", "relation": "supporta", "tail": "il Coordinatore", "tail_type": "Persona"}, {"head": "Commissione Didattica", "head_type": "Commissione", "relation": "coadiuva", "tail": ""}]]