[[{"head": "University of Bologna", "head_type": "Organization", "relation": "located_in", "tail": "Cesena", "tail_type": "Location"}, {"head": "Virtual Fair", "head_type": "Event", "relation": "has_participant", "tail": "International students", "tail_type": "Group"}, {"head": "Facebook", "head_type": "SocialMedia", "relation": "has_account", "tail": "Unibo", "tail_type": "Organization"}, {"head": "Twitter", "head_type": "SocialMedia", "relation": "has_account", "tail": "Unibo", "tail_type": "Organization"}, {"head": "LinkedIn", "head_type": "SocialMedia", "relation": "has_account", "tail": "Unibo", "tail_type": "Organization"}, {"head": "University of Bologna", "head_type": "Organization", "relation": "has_app", "tail": "MyUnibo", "tail_type": "App"}, {"head": "University of Bologna", "head_type": "Organization", "relation": "has_app", "tail": "My Alma Orienta", "tail_type": "App"}, {"head": "University of Bologna", "head_type": "Organization", "relation": "has_app", "tail": "Job Placement Unibo", "tail_type": "App"}, {"head": "Alumni Association", "head_type": "Organization", "relation": "has_website", "tail": "https://site.unibo.it/alumni-association/it", "tail_type": "URL"}, {"head": "University of Bologna", "head_type": "Organization", "relation": "has_cookie_settings", "tail": "https://www.unibo.it/en/university/cookie-settings", "tail_type": "URL"}], [{"head": "University of Bologna", "head_type": "Organization", "relation": "located_in", "tail": "Cesena", "tail_type": "Location"}, {"head": "Virtual Fair", "head_type": "Event", "relation": "has_participant", "tail": "International students", "tail_type": "Group"}, {"head": "Facebook", "head_type": "SocialMedia", "relation": "has_account", "tail": "Unibo", "tail_type": "Organization"}, {"head": "Twitter", "head_type": "SocialMedia", "relation": "has_account", "tail": "Unibo", "tail_type": "Organization"}, {"head": "LinkedIn", "head_type": "SocialMedia", "relation": "has_account", "tail": "Unibo", "tail_type": "Organization"}, {"head": "University of Bologna", "head_type": "Organization", "relation": "has_app", "tail": "MyUnibo", "tail_type": "App"}, {"head": "University of Bologna", "head_type": "Organization", "relation": "has_app", "tail": "My Alma Orienta", "tail_type": "App"}, {"head": "University of Bologna", "head_type": "Organization", "relation": "has_app", "tail": "Job Placement Unibo", "tail_type": "App"}, {"head": "Alumni Association", "head_type": "Organization", "relation": "has_website", "tail": "https://site.unibo.it/alumni-association/it", "tail_type": "URL"}, {"head": "University of Bologna", "head_type": "Organization", "relation": "has_cookie_settings", "tail": "https://www.unibo.it/en/university/cookie-settings", "tail_type": "URL"}], [{"head": "University of Bologna", "head_type": "Organization", "relation": "located_in", "tail": "Cesena", "tail_type": "Location"}, {}]]