[[{"head": "Ingegneria", "head_type": "subject", "relation": "is_related_to", "tail": "Scienze", "tail_type": "subject"}, {"head": "Scienze", "head_type": "subject", "relation": "is_related_to", "tail": "Architettura", "tail_type": "subject"}, {"head": "Cesena", "head_type": "location", "relation": "is_host_to", "tail": "riunione", "tail_type": "event"}, {"head": "riunione", "head_type": "event", "relation": "is_about", "tail": "candidatura", "tail_type": "concept"}, {"head": "candidatura", "head_type": "concept", "relation": "is_related_to", "tail": "Ingegneria", "tail_type": "subject"}, {"head": "Italiano", "head_type": "language", "relation": "is_used_in", "tail": "incontro", "tail_type": "event"}, {"head": "incontro", "head_type": "event", "relation": "is_about", "tail": "erasmus", "tail_type": "concept"}, {"head": "erasmus", "head_type": "concept", "relation": "is_related_to", "tail": "studiare", "tail_type": "verb"}, {"head": "studiare", "head_type": "verb", "relation": "is_used_by", "tail": "studenti", "tail_type": "entity"}, {"head": "studenti", "head_type": "entity", "relation": "is_part_of", "tail": "unibo", "tail_type": "organization"}, {"head": "unibo", "head_type": "organization", "relation": "is_host_to", "tail": "studio", "tail_type": "event"}], [{"head": "Ingegneria", "head_type": "subject", "relation": "is_related_to", "tail": "Scienze", "tail_type": "subject"}, {"head": "Scienze", "head_type": "subject", "relation": "is_related_to", "tail": "Architettura", "tail_type": "subject"}, {"head": "Cesena", "head_type": "location", "relation": "is_host_to", "tail": "riunione", "tail_type": "event"}, {"head": "riunione", "head_type": "event", "relation": "is_about", "tail": "candidatura", "tail_type": "concept"}, {"head": "candidatura", "head_type": "concept", "relation": "is_related_to", "tail": "Ingegneria", "tail_type": "subject"}, {"head": "Italiano", "head_type": "language", "relation": "is_used_in", "tail": "incontro", "tail_type": "event"}, {"head": "incontro", "head_type": "event", "relation": "is_about", "tail": "erasmus", "tail_type": "concept"}, {"head": "erasmus", "head_type": "concept", "relation": "is_related_to", "tail": "studiare", "tail_type": "verb"}, {"head": "studiare", "head_type": "verb", "relation": "is_used_by", "tail": "studenti", "tail_type": "entity"}, {"head": "studenti", "head_type": "entity", "relation": "is_part_of", "tail": "unibo", "tail_type": "organization"}, {"head": "unibo", "head_type": "organization", "relation": "is_host_to", "tail": "studio", "tail_type": "event"}], [{"head": "Ingegneria", "head_type": "subject", "relation": "is_related_to", "tail": "Scienze", "tail_type": "subject"}, {"head": "Scienze", "head_type": "subject", "relation": "is_related_to", "tail": "Architettura", "tail_type": "subject"}, {"head": "Cesena", "head_type": "location", "relation": "is_host_to", "tail": "riunione", "tail_type": "event"}, {"head": "riunione", "head_type": "event", "relation": "is_about", "tail": "candidatura", "tail_type": "concept"}, {"head": "candidatura", "head_type": "concept", "relation": "is_related_to", "tail": "Ingegneria"}]]