[{"head": "Distributed Systems", "head_type": "Course", "relation": "period", "tail": "1", "tail_type": "Period"}, {"head": "Distributed Systems", "head_type": "Course", "relation": "type", "tail": "B", "tail_type": "Type"}, {"head": "Distributed Systems", "head_type": "Course", "relation": "ssd", "tail": "ING-INF/05", "tail_type": "Disciplinary-scientific area"}, {"head": "Distributed Systems", "head_type": "Course", "relation": "cfu", "tail": "6", "tail_type": "Credits"}, {"head": "Embedded Systems and Internet of Things", "head_type": "Course", "relation": "period", "tail": "1", "tail_type": "Period"}, {"head": "Embedded Systems and Internet of Things", "head_type": "Course", "relation": "type", "tail": "B", "tail_type": "Type"}, {"head": "Embedded Systems and Internet of Things", "head_type": "Course", "relation": "ssd", "tail": "ING-INF/05", "tail_type": "Disciplinary-scientific area"}, {"head": "Embedded Systems and Internet of Things", "head_type": "Course", "relation": "cfu", "tail": "6", "tail_type": "Credits"}, {"head": "Fundamentals of Management", "head_type": "Course", "relation": "period", "tail": "1", "tail_type": "Period"}, {"head": "Fundamentals of Management", "head_type": "Course", "relation": "type", "tail": "C", "tail_type": "Type"}, {"head": "Fundamentals of Management", "head_type": "Course", "relation": "ssd", "tail": "SECS-P/10", "tail_type": "Disciplinary-scientific area"}, {"head": "Fundamentals of Management", "head_type": "Course", "relation": "cfu", "tail": "6", "tail_type": "Credits"}, {"head": "Organization, Teams and Digital Leadership", "head_type": "Course", "relation": "period", "tail": "1", "tail_type": "Period"}, {"head": "Organization, Teams and Digital Leadership", "head_type": "Course", "relation": "type", "tail": "C", "tail_type": "Type"}, {"head": "Organization, Teams and Digital Leadership", "head_type": "Course", "relation": "ssd", "tail": "SECS-P/10", "tail_type": "Disciplinary-scientific area"}, {"head": "Organization, Teams and Digital Leadership", "head_type": "Course", "relation": "cfu", "tail": "6", "tail_type": "Credits"}, {"head": "Machine Learning and Data Mining", "head_type": "Course", "relation": "period", "tail": "1", "tail_type": "Period"}, {"head": "Machine Learning and Data Mining", "head_type": "Course", "relation": "type", "tail": "B", "tail_type": "Type"}, {"head": "Machine Learning and Data Mining", "head_type": "Course", "relation": "ssd", "tail": "ING-INF/05", "tail_type": "Disciplinary-scientific area"}, {"head": "Machine Learning and Data Mining", "head_type": "Course", "relation": "cfu", "tail": "6", "tail_type": "Credits"}, {"head": "Cybersecurity", "head_type": "Course"}]